jsonrpcobjects/__init__.py
jsonrpcobjects/errors.py
jsonrpcobjects/objects.py
jsonrpcobjects/parse.py
jsonrpcobjects/py.typed
jsonrpc2_objects-4.3.2.dist-info/LICENSE
jsonrpc2_objects-4.3.2.dist-info/METADATA
jsonrpc2_objects-4.3.2.dist-info/WHEEL
jsonrpc2_objects-4.3.2.dist-info/RECORD
