Metadata-Version: 2.3
Name: jsonrpc2-objects
Version: 4.3.2
Summary: A collection of objects for use in JSON-RPC 2.0 implementations.
License: MIT
Author: Matthew Burkard
Author-email: matthewjburkard@gmail.com
Requires-Python: >=3.9,<4.0
Classifier: License :: OSI Approved :: MIT License
Classifier: Programming Language :: Python :: 3
Classifier: Programming Language :: Python :: 3.9
Classifier: Programming Language :: Python :: 3.10
Classifier: Programming Language :: Python :: 3.11
Classifier: Programming Language :: Python :: 3.12
Classifier: Programming Language :: Python :: 3.13
Requires-Dist: pydantic (>=2.5.1,<3.0.0)
Project-URL: Homepage, https://gitlab.com/mburkard/jsonrpc2-objects
Project-URL: Repository, https://gitlab.com/mburkard/jsonrpc2-objects
